<annotation>
	<folder>data</folder>
	<filename>184.jpg</filename>
	<path>/Users/HoraceCai/Desktop/540 dl/Data/data/184.jpg</path>
	<source>
		<database>Unknown</database>
	</source>
	<size>
		<width>612</width>
		<height>446</height>
		<depth>3</depth>
	</size>
	<segmented>0</segmented>
	<object>
		<name>fresh_banana</name>
		<pose>Unspecified</pose>
		<truncated>0</truncated>
		<difficult>0</difficult>
		<bndbox>
			<xmin>381</xmin>
			<ymin>53</ymin>
			<xmax>537</xmax>
			<ymax>375</ymax>
		</bndbox>
	</object>
	<object>
		<name>rotten_banana</name>
		<pose>Unspecified</pose>
		<truncated>0</truncated>
		<difficult>0</difficult>
		<bndbox>
			<xmin>57</xmin>
			<ymin>70</ymin>
			<xmax>202</xmax>
			<ymax>401</ymax>
		</bndbox>
	</object>
	<object>
		<name>rotten_banana</name>
		<pose>Unspecified</pose>
		<truncated>0</truncated>
		<difficult>0</difficult>
		<bndbox>
			<xmin>155</xmin>
			<ymin>53</ymin>
			<xmax>333</xmax>
			<ymax>379</ymax>
		</bndbox>
	</object>
	<object>
		<name>rotten_banana</name>
		<pose>Unspecified</pose>
		<truncated>0</truncated>
		<difficult>0</difficult>
		<bndbox>
			<xmin>220</xmin>
			<ymin>59</ymin>
			<xmax>438</xmax>
			<ymax>388</ymax>
		</bndbox>
	</object>
</annotation>
