<annotation>
	<folder>data</folder>
	<filename>193.jpg</filename>
	<path>/Users/HoraceCai/Desktop/540 dl/Data/data/193.jpg</path>
	<source>
		<database>Unknown</database>
	</source>
	<size>
		<width>612</width>
		<height>413</height>
		<depth>3</depth>
	</size>
	<segmented>0</segmented>
	<object>
		<name>rotten_banana</name>
		<pose>Unspecified</pose>
		<truncated>0</truncated>
		<difficult>0</difficult>
		<bndbox>
			<xmin>155</xmin>
			<ymin>63</ymin>
			<xmax>259</xmax>
			<ymax>314</ymax>
		</bndbox>
	</object>
	<object>
		<name>fresh_banana</name>
		<pose>Unspecified</pose>
		<truncated>0</truncated>
		<difficult>0</difficult>
		<bndbox>
			<xmin>318</xmin>
			<ymin>29</ymin>
			<xmax>418</xmax>
			<ymax>323</ymax>
		</bndbox>
	</object>
</annotation>
